{"openapi":"3.0.1","info":{"title":"XXX用户系统API","description":"Knife4j集成springdoc-openapi示例","termsOfService":"http://doc.xiaominfo.com","license":{"name":"Apache 2.0","url":"http://doc.xiaominfo.com"},"version":"1.0"},"servers":[{"url":"http://localhost:8080","description":"Generated server url"}],"tags":[{"name":"EmployeeController","description":"员工管理"}],"paths":{"/user/order/payment":{"put":{"tags":["order-controller"],"operationId":"payment","requestBody":{"content":{"application/json":{"schema":{"$ref":"#/components/schemas/OrdersPaymentDTO"}}},"required":true},"responses":{"200":{"description":"OK","content":{"*/*":{"schema":{"$ref":"#/components/schemas/ResultOrderPaymentVO"}}}}}}},"/user/order/cancel/{id}":{"put":{"tags":["order-controller"],"operationId":"cancel","parameters":[{"name":"id","in":"path","required":true,"schema":{"type":"integer","format":"int64"}}],"responses":{"200":{"description":"OK","content":{"*/*":{"schema":{"$ref":"#/components/schemas/ResultString"}}}}}}},"/user/addressBook":{"put":{"tags":["address-book-controller"],"operationId":"update","requestBody":{"content":{"application/json":{"schema":{"$ref":"#/components/schemas/AddressBook"}}},"required":true},"responses":{"200":{"description":"OK","content":{"*/*":{"schema":{"$ref":"#/components/schemas/ResultString"}}}}}},"post":{"tags":["address-book-controller"],"operationId":"save","requestBody":{"content":{"application/json":{"schema":{"$ref":"#/components/schemas/AddressBook"}}},"required":true},"responses":{"200":{"description":"OK","content":{"*/*":{"schema":{"$ref":"#/components/schemas/ResultString"}}}}}},"delete":{"tags":["address-book-controller"],"operationId":"deleteById","parameters":[{"name":"id","in":"query","required":true,"schema":{"type":"integer","format":"int64"}}],"responses":{"200":{"description":"OK","content":{"*/*":{"schema":{"$ref":"#/components/schemas/ResultString"}}}}}}},"/user/addressBook/default":{"get":{"tags":["address-book-controller"],"operationId":"getDefault","responses":{"200":{"description":"OK","content":{"*/*":{"schema":{"$ref":"#/components/schemas/ResultAddressBook"}}}}}},"put":{"tags":["address-book-controller"],"operationId":"setDefault","requestBody":{"content":{"application/json":{"schema":{"$ref":"#/components/schemas/AddressBook"}}},"required":true},"responses":{"200":{"description":"OK","content":{"*/*":{"schema":{"$ref":"#/components/schemas/ResultString"}}}}}}},"/admin/shop/{status}":{"put":{"tags":["shop-controller"],"operationId":"setShopStatus","parameters":[{"name":"status","in":"path","required":true,"schema":{"type":"integer","format":"int32"}}],"responses":{"200":{"description":"OK","content":{"*/*":{"schema":{"$ref":"#/components/schemas/ResultString"}}}}}}},"/admin/setmeal":{"put":{"tags":["setmeal-controller"],"operationId":"update_1","requestBody":{"content":{"application/json":{"schema":{"$ref":"#/components/schemas/SetmealDTO"}}},"required":true},"responses":{"200":{"description":"OK","content":{"*/*":{"schema":{"$ref":"#/components/schemas/ResultString"}}}}}},"post":{"tags":["setmeal-controller"],"operationId":"save_1","requestBody":{"content":{"application/json":{"schema":{"$ref":"#/components/schemas/SetmealDTO"}}},"required":true},"responses":{"200":{"description":"OK","content":{"*/*":{"schema":{"$ref":"#/components/schemas/ResultString"}}}}}},"delete":{"tags":["setmeal-controller"],"operationId":"delete","parameters":[{"name":"ids","in":"query","required":true,"schema":{"type":"array","items":{"type":"integer","format":"int64"}}}],"responses":{"200":{"description":"OK","content":{"*/*":{"schema":{"$ref":"#/components/schemas/ResultString"}}}}}}},"/admin/order/rejection":{"put":{"tags":["order-controller"],"operationId":"rejection","requestBody":{"content":{"application/json":{"schema":{"$ref":"#/components/schemas/OrdersRejectionDTO"}}},"required":true},"responses":{"200":{"description":"OK","content":{"*/*":{"schema":{"$ref":"#/components/schemas/ResultString"}}}}}}},"/admin/order/delivery/{id}":{"put":{"tags":["order-controller"],"operationId":"delivery","parameters":[{"name":"id","in":"path","required":true,"schema":{"type":"integer","format":"int64"}}],"responses":{"200":{"description":"OK","content":{"*/*":{"schema":{"$ref":"#/components/schemas/ResultString"}}}}}}},"/admin/order/confirm":{"put":{"tags":["order-controller"],"operationId":"confirm","requestBody":{"content":{"application/json":{"schema":{"$ref":"#/components/schemas/OrdersConfirmDTO"}}},"required":true},"responses":{"200":{"description":"OK","content":{"*/*":{"schema":{"$ref":"#/components/schemas/ResultString"}}}}}}},"/admin/order/complete/{id}":{"put":{"tags":["order-controller"],"operationId":"complete","parameters":[{"name":"id","in":"path","required":true,"schema":{"type":"integer","format":"int64"}}],"responses":{"200":{"description":"OK","content":{"*/*":{"schema":{"$ref":"#/components/schemas/ResultString"}}}}}}},"/admin/order/cancel":{"put":{"tags":["order-controller"],"operationId":"cancel_1","requestBody":{"content":{"application/json":{"schema":{"$ref":"#/components/schemas/OrdersCancelDTO"}}},"required":true},"responses":{"200":{"description":"OK","content":{"*/*":{"schema":{"$ref":"#/components/schemas/ResultString"}}}}}}},"/admin/employee":{"put":{"tags":["EmployeeController"],"operationId":"update_2","requestBody":{"content":{"application/json":{"schema":{"$ref":"#/components/schemas/EmployeeDTO"}}},"required":true},"responses":{"200":{"description":"OK","content":{"*/*":{"schema":{"$ref":"#/components/schemas/ResultString"}}}}}},"post":{"tags":["EmployeeController"],"operationId":"save_2","requestBody":{"content":{"application/json":{"schema":{"$ref":"#/components/schemas/EmployeeDTO"}}},"required":true},"responses":{"200":{"description":"OK","content":{"*/*":{"schema":{"$ref":"#/components/schemas/ResultString"}}}}}}},"/admin/dish":{"put":{"tags":["dish-controller"],"operationId":"update_3","requestBody":{"content":{"application/json":{"schema":{"$ref":"#/components/schemas/DishDTO"}}},"required":true},"responses":{"200":{"description":"OK","content":{"*/*":{"schema":{"$ref":"#/components/schemas/ResultString"}}}}}},"post":{"tags":["dish-controller"],"operationId":"save_3","requestBody":{"content":{"application/json":{"schema":{"$ref":"#/components/schemas/DishDTO"}}},"required":true},"responses":{"200":{"description":"OK","content":{"*/*":{"schema":{"$ref":"#/components/schemas/ResultString"}}}}}},"delete":{"tags":["dish-controller"],"operationId":"delete_1","parameters":[{"name":"ids","in":"query","required":true,"schema":{"type":"array","items":{"type":"integer","format":"int64"}}}],"responses":{"200":{"description":"OK","content":{"*/*":{"schema":{"$ref":"#/components/schemas/ResultString"}}}}}}},"/admin/category":{"put":{"tags":["category-controller"],"operationId":"update_4","requestBody":{"content":{"application/json":{"schema":{"$ref":"#/components/schemas/CategoryDTO"}}},"required":true},"responses":{"200":{"description":"OK","content":{"*/*":{"schema":{"$ref":"#/components/schemas/ResultString"}}}}}},"post":{"tags":["category-controller"],"operationId":"save_4","requestBody":{"content":{"application/json":{"schema":{"$ref":"#/components/schemas/CategoryDTO"}}},"required":true},"responses":{"200":{"description":"OK","content":{"*/*":{"schema":{"$ref":"#/components/schemas/ResultString"}}}}}},"delete":{"tags":["category-controller"],"operationId":"deleteById_1","parameters":[{"name":"id","in":"query","required":true,"schema":{"type":"integer","format":"int64"}}],"responses":{"200":{"description":"OK","content":{"*/*":{"schema":{"$ref":"#/components/schemas/ResultString"}}}}}}},"/user/user/login":{"post":{"tags":["user-controller"],"operationId":"login","requestBody":{"content":{"application/json":{"schema":{"$ref":"#/components/schemas/UserLoginDTO"}}},"required":true},"responses":{"200":{"description":"OK","content":{"*/*":{"schema":{"$ref":"#/components/schemas/ResultUserLoginVO"}}}}}}},"/user/shoppingCart/sub":{"post":{"tags":["shopping-cart-controller"],"operationId":"sub","requestBody":{"content":{"application/json":{"schema":{"$ref":"#/components/schemas/ShoppingCartDTO"}}},"required":true},"responses":{"200":{"description":"OK","content":{"*/*":{"schema":{"$ref":"#/components/schemas/ResultString"}}}}}}},"/user/shoppingCart/add":{"post":{"tags":["shopping-cart-controller"],"operationId":"add","requestBody":{"content":{"application/json":{"schema":{"$ref":"#/components/schemas/ShoppingCartDTO"}}},"required":true},"responses":{"200":{"description":"OK","content":{"*/*":{"schema":{"$ref":"#/components/schemas/ResultString"}}}}}}},"/user/order/submit":{"post":{"tags":["order-controller"],"operationId":"submit","requestBody":{"content":{"application/json":{"schema":{"$ref":"#/components/schemas/OrdersSubmitDTO"}}},"required":true},"responses":{"200":{"description":"OK","content":{"*/*":{"schema":{"$ref":"#/components/schemas/ResultOrderSubmitVO"}}}}}}},"/user/order/repetition/{id}":{"post":{"tags":["order-controller"],"operationId":"repetition","parameters":[{"name":"id","in":"path","required":true,"schema":{"type":"integer","format":"int64"}}],"responses":{"200":{"description":"OK","content":{"*/*":{"schema":{"$ref":"#/components/schemas/ResultString"}}}}}}},"/admin/setmeal/status/{status}":{"post":{"tags":["setmeal-controller"],"operationId":"startOrStop","parameters":[{"name":"status","in":"path","required":true,"schema":{"type":"integer","format":"int32"}},{"name":"id","in":"query","required":true,"schema":{"type":"integer","format":"int64"}}],"responses":{"200":{"description":"OK","content":{"*/*":{"schema":{"$ref":"#/components/schemas/ResultString"}}}}}}},"/admin/employee/status/{status}":{"post":{"tags":["EmployeeController"],"operationId":"startOrStop_1","parameters":[{"name":"status","in":"path","required":true,"schema":{"type":"integer","format":"int32"}},{"name":"id","in":"query","required":true,"schema":{"type":"integer","format":"int64"}}],"responses":{"200":{"description":"OK","content":{"*/*":{"schema":{"$ref":"#/components/schemas/ResultString"}}}}}}},"/admin/employee/logout":{"post":{"tags":["EmployeeController"],"operationId":"logout","responses":{"200":{"description":"OK","content":{"*/*":{"schema":{"$ref":"#/components/schemas/ResultString"}}}}}}},"/admin/employee/login":{"post":{"tags":["EmployeeController"],"summary":"登录","operationId":"login_1","parameters":[{"name":"employeeLoginDTO","in":"query","description":"登录信息","required":true}],"requestBody":{"content":{"application/json":{"schema":{"$ref":"#/components/schemas/EmployeeLoginDTO"}}},"required":true},"responses":{"200":{"description":"OK","content":{"*/*":{"schema":{"$ref":"#/components/schemas/ResultEmployeeLoginVO"}}}}}}},"/admin/dish/status/{status}":{"post":{"tags":["dish-controller"],"operationId":"startOrStop_2","parameters":[{"name":"status","in":"path","required":true,"schema":{"type":"integer","format":"int32"}},{"name":"id","in":"query","required":true,"schema":{"type":"integer","format":"int64"}}],"responses":{"200":{"description":"OK","content":{"*/*":{"schema":{"$ref":"#/components/schemas/ResultString"}}}}}}},"/admin/common/upload":{"post":{"tags":["common-controller"],"operationId":"upload","responses":{"200":{"description":"OK","content":{"*/*":{"schema":{"$ref":"#/components/schemas/ResultString"}}}}}}},"/admin/category/status/{status}":{"post":{"tags":["category-controller"],"operationId":"startOrStop_3","parameters":[{"name":"status","in":"path","required":true,"schema":{"type":"integer","format":"int32"}},{"name":"id","in":"query","required":true,"schema":{"type":"integer","format":"int64"}}],"responses":{"200":{"description":"OK","content":{"*/*":{"schema":{"$ref":"#/components/schemas/ResultString"}}}}}}},"/user/shoppingCart/list":{"get":{"tags":["shopping-cart-controller"],"operationId":"list","responses":{"200":{"description":"OK","content":{"*/*":{"schema":{"$ref":"#/components/schemas/ResultListShoppingCart"}}}}}}},"/user/shop/status":{"get":{"tags":["shop-controller"],"operationId":"getShopStatus","responses":{"200":{"description":"OK","content":{"*/*":{"schema":{"$ref":"#/components/schemas/ResultInteger"}}}}}}},"/user/setmeal/list":{"get":{"tags":["setmeal-controller"],"operationId":"list_1","parameters":[{"name":"categoryId","in":"query","required":true,"schema":{"type":"integer","format":"int64"}}],"responses":{"200":{"description":"OK","content":{"*/*":{"schema":{"$ref":"#/components/schemas/ResultListSetmeal"}}}}}}},"/user/setmeal/dish/{id}":{"get":{"tags":["setmeal-controller"],"operationId":"dishList","parameters":[{"name":"id","in":"path","required":true,"schema":{"type":"integer","format":"int64"}}],"responses":{"200":{"description":"OK","content":{"*/*":{"schema":{"$ref":"#/components/schemas/ResultListDishItemVO"}}}}}}},"/user/order/reminder/{id}":{"get":{"tags":["order-controller"],"operationId":"reminder","parameters":[{"name":"id","in":"path","required":true,"schema":{"type":"integer","format":"int64"}}],"responses":{"200":{"description":"OK","content":{"*/*":{"schema":{"$ref":"#/components/schemas/ResultString"}}}}}}},"/user/order/orderDetail/{id}":{"get":{"tags":["order-controller"],"operationId":"details","parameters":[{"name":"id","in":"path","required":true,"schema":{"type":"integer","format":"int64"}}],"responses":{"200":{"description":"OK","content":{"*/*":{"schema":{"$ref":"#/components/schemas/ResultOrderVO"}}}}}}},"/user/order/historyOrders":{"get":{"tags":["order-controller"],"operationId":"page","parameters":[{"name":"page","in":"query","required":true,"schema":{"type":"integer","format":"int32"}},{"name":"pageSize","in":"query","required":true,"schema":{"type":"integer","format":"int32"}},{"name":"status","in":"query","required":true,"schema":{"type":"integer","format":"int32"}}],"responses":{"200":{"description":"OK","content":{"*/*":{"schema":{"$ref":"#/components/schemas/ResultPageResultOrderVO"}}}}}}},"/user/dish/list":{"get":{"tags":["dish-controller"],"operationId":"list_2","parameters":[{"name":"categoryId","in":"query","required":true,"schema":{"type":"integer","format":"int64"}}],"responses":{"200":{"description":"OK","content":{"*/*":{"schema":{"$ref":"#/components/schemas/ResultListDishVO"}}}}}}},"/user/category/list":{"get":{"tags":["category-controller"],"operationId":"list_3","parameters":[{"name":"type","in":"query","required":true,"schema":{"type":"integer","format":"int32"}}],"responses":{"200":{"description":"OK","content":{"*/*":{"schema":{"$ref":"#/components/schemas/ResultListCategory"}}}}}}},"/user/addressBook/{id}":{"get":{"tags":["address-book-controller"],"operationId":"getById","parameters":[{"name":"id","in":"path","required":true,"schema":{"type":"integer","format":"int64"}}],"responses":{"200":{"description":"OK","content":{"*/*":{"schema":{"$ref":"#/components/schemas/ResultAddressBook"}}}}}}},"/user/addressBook/list":{"get":{"tags":["address-book-controller"],"operationId":"list_4","responses":{"200":{"description":"OK","content":{"*/*":{"schema":{"$ref":"#/components/schemas/ResultListAddressBook"}}}}}}},"/admin/workspace/overviewSetmeals":{"get":{"tags":["work-space-controller"],"operationId":"setmealOverView","responses":{"200":{"description":"OK","content":{"*/*":{"schema":{"$ref":"#/components/schemas/ResultSetmealOverViewVO"}}}}}}},"/admin/workspace/overviewOrders":{"get":{"tags":["work-space-controller"],"operationId":"orderOverView","responses":{"200":{"description":"OK","content":{"*/*":{"schema":{"$ref":"#/components/schemas/ResultOrderOverViewVO"}}}}}}},"/admin/workspace/overviewDishes":{"get":{"tags":["work-space-controller"],"operationId":"dishOverView","responses":{"200":{"description":"OK","content":{"*/*":{"schema":{"$ref":"#/components/schemas/ResultDishOverViewVO"}}}}}}},"/admin/workspace/businessData":{"get":{"tags":["work-space-controller"],"operationId":"businessData","responses":{"200":{"description":"OK","content":{"*/*":{"schema":{"$ref":"#/components/schemas/ResultBusinessDataVO"}}}}}}},"/admin/shop/status":{"get":{"tags":["shop-controller"],"operationId":"getShopStatus_1","responses":{"200":{"description":"OK","content":{"*/*":{"schema":{"$ref":"#/components/schemas/ResultInteger"}}}}}}},"/admin/setmeal/{id}":{"get":{"tags":["setmeal-controller"],"operationId":"getById_1","parameters":[{"name":"id","in":"path","required":true,"schema":{"type":"integer","format":"int64"}}],"responses":{"200":{"description":"OK","content":{"*/*":{"schema":{"$ref":"#/components/schemas/ResultSetmealVO"}}}}}}},"/admin/setmeal/page":{"get":{"tags":["setmeal-controller"],"operationId":"page_1","parameters":[{"name":"page","in":"query","required":false,"schema":{"type":"integer","format":"int32"}},{"name":"pageSize","in":"query","required":false,"schema":{"type":"integer","format":"int32"}},{"name":"name","in":"query","required":false,"schema":{"type":"string"}},{"name":"categoryId","in":"query","required":false,"schema":{"type":"integer","format":"int32"}},{"name":"status","in":"query","required":false,"schema":{"type":"integer","format":"int32"}}],"responses":{"200":{"description":"OK","content":{"*/*":{"schema":{"$ref":"#/components/schemas/ResultPageResultSetmealVO"}}}}}}},"/admin/report/userStatistics":{"get":{"tags":["report-controller"],"operationId":"userStatistics","parameters":[{"name":"begin","in":"query","required":true,"schema":{"type":"string","format":"date"}},{"name":"end","in":"query","required":true,"schema":{"type":"string","format":"date"}}],"responses":{"200":{"description":"OK","content":{"*/*":{"schema":{"$ref":"#/components/schemas/ResultUserReportVO"}}}}}}},"/admin/report/turnoverStatistics":{"get":{"tags":["report-controller"],"operationId":"turnoverStatistics","parameters":[{"name":"begin","in":"query","required":true,"schema":{"type":"string","format":"date"}},{"name":"end","in":"query","required":true,"schema":{"type":"string","format":"date"}}],"responses":{"200":{"description":"OK","content":{"*/*":{"schema":{"$ref":"#/components/schemas/ResultTurnoverReportVO"}}}}}}},"/admin/report/top10":{"get":{"tags":["report-controller"],"operationId":"top10","parameters":[{"name":"begin","in":"query","required":true,"schema":{"type":"string","format":"date"}},{"name":"end","in":"query","required":true,"schema":{"type":"string","format":"date"}}],"responses":{"200":{"description":"OK","content":{"*/*":{"schema":{"$ref":"#/components/schemas/ResultSalesTop10ReportVO"}}}}}}},"/admin/report/ordersStatistics":{"get":{"tags":["report-controller"],"operationId":"orderStatistics","parameters":[{"name":"begin","in":"query","required":true,"schema":{"type":"string","format":"date"}},{"name":"end","in":"query","required":true,"schema":{"type":"string","format":"date"}}],"responses":{"200":{"description":"OK","content":{"*/*":{"schema":{"$ref":"#/components/schemas/ResultOrderReportVO"}}}}}}},"/admin/report/export":{"get":{"tags":["report-controller"],"operationId":"exportExcel","responses":{"200":{"description":"OK"}}}},"/admin/order/statistics":{"get":{"tags":["order-controller"],"operationId":"statistics","responses":{"200":{"description":"OK","content":{"*/*":{"schema":{"$ref":"#/components/schemas/ResultOrderStatisticsVO"}}}}}}},"/admin/order/details/{id}":{"get":{"tags":["order-controller"],"operationId":"details_1","parameters":[{"name":"id","in":"path","required":true,"schema":{"type":"integer","format":"int64"}}],"responses":{"200":{"description":"OK","content":{"*/*":{"schema":{"$ref":"#/components/schemas/ResultOrderVO"}}}}}}},"/admin/order/conditionSearch":{"get":{"tags":["order-controller"],"operationId":"conditionSearch","parameters":[{"name":"page","in":"query","required":false,"schema":{"type":"integer","format":"int32"}},{"name":"pageSize","in":"query","required":false,"schema":{"type":"integer","format":"int32"}},{"name":"number","in":"query","required":false,"schema":{"type":"string"}},{"name":"phone","in":"query","required":false,"schema":{"type":"string"}},{"name":"status","in":"query","required":false,"schema":{"type":"integer","format":"int32"}},{"name":"beginTime","in":"query","required":false,"schema":{"type":"string","format":"date-time"}},{"name":"endTime","in":"query","required":false,"schema":{"type":"string","format":"date-time"}},{"name":"userId","in":"query","required":false,"schema":{"type":"integer","format":"int64"}}],"responses":{"200":{"description":"OK","content":{"*/*":{"schema":{"$ref":"#/components/schemas/ResultPageResultOrderVO"}}}}}}},"/admin/employee/{id}":{"get":{"tags":["EmployeeController"],"operationId":"getById_2","parameters":[{"name":"id","in":"path","required":true,"schema":{"type":"integer","format":"int64"}}],"responses":{"200":{"description":"OK","content":{"*/*":{"schema":{"$ref":"#/components/schemas/ResultEmployee"}}}}}}},"/admin/employee/page":{"get":{"tags":["EmployeeController"],"operationId":"page_2","parameters":[{"name":"name","in":"query","required":false,"schema":{"type":"string"}},{"name":"page","in":"query","required":false,"schema":{"type":"integer","format":"int32"}},{"name":"pageSize","in":"query","required":false,"schema":{"type":"integer","format":"int32"}}],"responses":{"200":{"description":"OK","content":{"*/*":{"schema":{"$ref":"#/components/schemas/ResultPageResultEmployee"}}}}}}},"/admin/dish/{id}":{"get":{"tags":["dish-controller"],"operationId":"getById_3","parameters":[{"name":"id","in":"path","required":true,"schema":{"type":"integer","format":"int64"}}],"responses":{"200":{"description":"OK","content":{"*/*":{"schema":{"$ref":"#/components/schemas/ResultDishVO"}}}}}}},"/admin/dish/page":{"get":{"tags":["dish-controller"],"operationId":"page_3","parameters":[{"name":"page","in":"query","required":false,"schema":{"type":"integer","format":"int32"}},{"name":"pageSize","in":"query","required":false,"schema":{"type":"integer","format":"int32"}},{"name":"name","in":"query","required":false,"schema":{"type":"string"}},{"name":"categoryId","in":"query","required":false,"schema":{"type":"integer","format":"int32"}},{"name":"status","in":"query","required":false,"schema":{"type":"integer","format":"int32"}}],"responses":{"200":{"description":"OK","content":{"*/*":{"schema":{"$ref":"#/components/schemas/ResultPageResultDishVO"}}}}}}},"/admin/dish/list":{"get":{"tags":["dish-controller"],"operationId":"list_5","parameters":[{"name":"categoryId","in":"query","required":true,"schema":{"type":"integer","format":"int64"}}],"responses":{"200":{"description":"OK","content":{"*/*":{"schema":{"$ref":"#/components/schemas/ResultListDish"}}}}}}},"/admin/category/page":{"get":{"tags":["category-controller"],"operationId":"page_4","parameters":[{"name":"page","in":"query","required":false,"schema":{"type":"integer","format":"int32"}},{"name":"pageSize","in":"query","required":false,"schema":{"type":"integer","format":"int32"}},{"name":"name","in":"query","required":false,"schema":{"type":"string"}},{"name":"type","in":"query","required":false,"schema":{"type":"integer","format":"int32"}}],"responses":{"200":{"description":"OK","content":{"*/*":{"schema":{"$ref":"#/components/schemas/ResultPageResultCategory"}}}}}}},"/admin/category/list":{"get":{"tags":["category-controller"],"operationId":"list_6","parameters":[{"name":"type","in":"query","required":true,"schema":{"type":"integer","format":"int32"}}],"responses":{"200":{"description":"OK","content":{"*/*":{"schema":{"$ref":"#/components/schemas/ResultListCategory"}}}}}}},"/user/shoppingCart/clean":{"delete":{"tags":["shopping-cart-controller"],"operationId":"clean","responses":{"200":{"description":"OK","content":{"*/*":{"schema":{"$ref":"#/components/schemas/ResultString"}}}}}}},"/notify/paySuccess":{"get":{"tags":["pay-notify-controller"],"operationId":"paySuccessNotify","responses":{"200":{"description":"OK"}}},"put":{"tags":["pay-notify-controller"],"operationId":"paySuccessNotify_3","responses":{"200":{"description":"OK"}}},"post":{"tags":["pay-notify-controller"],"operationId":"paySuccessNotify_2","responses":{"200":{"description":"OK"}}},"delete":{"tags":["pay-notify-controller"],"operationId":"paySuccessNotify_5","responses":{"200":{"description":"OK"}}},"options":{"tags":["pay-notify-controller"],"operationId":"paySuccessNotify_6","responses":{"200":{"description":"OK"}}},"head":{"tags":["pay-notify-controller"],"operationId":"paySuccessNotify_1","responses":{"200":{"description":"OK"}}},"patch":{"tags":["pay-notify-controller"],"operationId":"paySuccessNotify_4","responses":{"200":{"description":"OK"}}}}},"components":{"schemas":{"OrdersPaymentDTO":{"type":"object","properties":{"orderNumber":{"type":"string"},"payMethod":{"type":"integer","format":"int32"}}},"OrderPaymentVO":{"type":"object","properties":{"nonceStr":{"type":"string"},"paySign":{"type":"string"},"timeStamp":{"type":"string"},"signType":{"type":"string"},"packageStr":{"type":"string"}}},"ResultOrderPaymentVO":{"type":"object","properties":{"code":{"type":"integer","format":"int32"},"msg":{"type":"string"},"data":{"$ref":"#/components/schemas/OrderPaymentVO"}}},"ResultString":{"type":"object","properties":{"code":{"type":"integer","format":"int32"},"msg":{"type":"string"},"data":{"type":"string"}}},"AddressBook":{"type":"object","properties":{"id":{"type":"integer","format":"int64"},"userId":{"type":"integer","format":"int64"},"consignee":{"type":"string"},"phone":{"type":"string"},"sex":{"type":"string"},"provinceCode":{"type":"string"},"provinceName":{"type":"string"},"cityCode":{"type":"string"},"cityName":{"type":"string"},"districtCode":{"type":"string"},"districtName":{"type":"string"},"detail":{"type":"string"},"label":{"type":"string"},"isDefault":{"type":"integer","format":"int32"}}},"SetmealDTO":{"type":"object","properties":{"id":{"type":"integer","format":"int64"},"categoryId":{"type":"integer","format":"int64"},"name":{"type":"string"},"price":{"type":"number"},"status":{"type":"integer","format":"int32"},"description":{"type":"string"},"image":{"type":"string"},"setmealDishes":{"type":"array","items":{"$ref":"#/components/schemas/SetmealDish"}}}},"SetmealDish":{"type":"object","properties":{"id":{"type":"integer","format":"int64"},"setmealId":{"type":"integer","format":"int64"},"dishId":{"type":"integer","format":"int64"},"name":{"type":"string"},"price":{"type":"number"},"copies":{"type":"integer","format":"int32"}}},"OrdersRejectionDTO":{"type":"object","properties":{"id":{"type":"integer","format":"int64"},"rejectionReason":{"type":"string"}}},"OrdersConfirmDTO":{"type":"object","properties":{"id":{"type":"integer","format":"int64"},"status":{"type":"integer","format":"int32"}}},"OrdersCancelDTO":{"type":"object","properties":{"id":{"type":"integer","format":"int64"},"cancelReason":{"type":"string"}}},"EmployeeDTO":{"type":"object","properties":{"id":{"type":"integer","format":"int64"},"username":{"type":"string"},"name":{"type":"string"},"phone":{"type":"string"},"sex":{"type":"string"},"idNumber":{"type":"string"}}},"DishDTO":{"type":"object","properties":{"id":{"type":"integer","format":"int64"},"name":{"type":"string"},"categoryId":{"type":"integer","format":"int64"},"price":{"type":"number"},"image":{"type":"string"},"description":{"type":"string"},"status":{"type":"integer","format":"int32"},"flavors":{"type":"array","items":{"$ref":"#/components/schemas/DishFlavor"}}}},"DishFlavor":{"type":"object","properties":{"id":{"type":"integer","format":"int64"},"dishId":{"type":"integer","format":"int64"},"name":{"type":"string"},"value":{"type":"string"}}},"CategoryDTO":{"type":"object","properties":{"id":{"type":"integer","format":"int64"},"type":{"type":"integer","format":"int32"},"name":{"type":"string"},"sort":{"type":"integer","format":"int32"}}},"UserLoginDTO":{"type":"object","properties":{"code":{"type":"string"}}},"ResultUserLoginVO":{"type":"object","properties":{"code":{"type":"integer","format":"int32"},"msg":{"type":"string"},"data":{"$ref":"#/components/schemas/UserLoginVO"}}},"UserLoginVO":{"type":"object","properties":{"id":{"type":"integer","format":"int64"},"openid":{"type":"string"},"token":{"type":"string"}}},"ShoppingCartDTO":{"type":"object","properties":{"dishId":{"type":"integer","format":"int64"},"setmealId":{"type":"integer","format":"int64"},"dishFlavor":{"type":"string"}}},"OrdersSubmitDTO":{"type":"object","properties":{"addressBookId":{"type":"integer","format":"int64"},"payMethod":{"type":"integer","format":"int32"},"remark":{"type":"string"},"estimatedDeliveryTime":{"type":"string","format":"date-time"},"deliveryStatus":{"type":"integer","format":"int32"},"tablewareNumber":{"type":"integer","format":"int32"},"tablewareStatus":{"type":"integer","format":"int32"},"packAmount":{"type":"integer","format":"int32"},"amount":{"type":"number"}}},"OrderSubmitVO":{"type":"object","properties":{"id":{"type":"integer","format":"int64"},"orderNumber":{"type":"string"},"orderAmount":{"type":"number"},"orderTime":{"type":"string","format":"date-time"}}},"ResultOrderSubmitVO":{"type":"object","properties":{"code":{"type":"integer","format":"int32"},"msg":{"type":"string"},"data":{"$ref":"#/components/schemas/OrderSubmitVO"}}},"EmployeeLoginDTO":{"type":"object","properties":{"username":{"type":"string"},"password":{"type":"string"}},"description":"登录信息"},"EmployeeLoginVO":{"type":"object","properties":{"id":{"type":"integer","format":"int64"},"userName":{"type":"string"},"name":{"type":"string"},"token":{"type":"string"}}},"ResultEmployeeLoginVO":{"type":"object","properties":{"code":{"type":"integer","format":"int32"},"msg":{"type":"string"},"data":{"$ref":"#/components/schemas/EmployeeLoginVO"}}},"ResultListShoppingCart":{"type":"object","properties":{"code":{"type":"integer","format":"int32"},"msg":{"type":"string"},"data":{"type":"array","items":{"$ref":"#/components/schemas/ShoppingCart"}}}},"ShoppingCart":{"type":"object","properties":{"id":{"type":"integer","format":"int64"},"name":{"type":"string"},"userId":{"type":"integer","format":"int64"},"dishId":{"type":"integer","format":"int64"},"setmealId":{"type":"integer","format":"int64"},"dishFlavor":{"type":"string"},"number":{"type":"integer","format":"int32"},"amount":{"type":"number"},"image":{"type":"string"},"createTime":{"type":"string","format":"date-time"}}},"ResultInteger":{"type":"object","properties":{"code":{"type":"integer","format":"int32"},"msg":{"type":"string"},"data":{"type":"integer","format":"int32"}}},"ResultListSetmeal":{"type":"object","properties":{"code":{"type":"integer","format":"int32"},"msg":{"type":"string"},"data":{"type":"array","items":{"$ref":"#/components/schemas/Setmeal"}}}},"Setmeal":{"type":"object","properties":{"id":{"type":"integer","format":"int64"},"categoryId":{"type":"integer","format":"int64"},"name":{"type":"string"},"price":{"type":"number"},"status":{"type":"integer","format":"int32"},"description":{"type":"string"},"image":{"type":"string"},"createTime":{"type":"string","format":"date-time"},"updateTime":{"type":"string","format":"date-time"},"createUser":{"type":"integer","format":"int64"},"updateUser":{"type":"integer","format":"int64"}}},"DishItemVO":{"type":"object","properties":{"name":{"type":"string"},"copies":{"type":"integer","format":"int32"},"image":{"type":"string"},"description":{"type":"string"}}},"ResultListDishItemVO":{"type":"object","properties":{"code":{"type":"integer","format":"int32"},"msg":{"type":"string"},"data":{"type":"array","items":{"$ref":"#/components/schemas/DishItemVO"}}}},"OrderDetail":{"type":"object","properties":{"id":{"type":"integer","format":"int64"},"name":{"type":"string"},"orderId":{"type":"integer","format":"int64"},"dishId":{"type":"integer","format":"int64"},"setmealId":{"type":"integer","format":"int64"},"dishFlavor":{"type":"string"},"number":{"type":"integer","format":"int32"},"amount":{"type":"number"},"image":{"type":"string"}}},"OrderVO":{"type":"object","properties":{"id":{"type":"integer","format":"int64"},"number":{"type":"string"},"status":{"type":"integer","format":"int32"},"userId":{"type":"integer","format":"int64"},"addressBookId":{"type":"integer","format":"int64"},"orderTime":{"type":"string","format":"date-time"},"checkoutTime":{"type":"string","format":"date-time"},"payMethod":{"type":"integer","format":"int32"},"payStatus":{"type":"integer","format":"int32"},"amount":{"type":"number"},"remark":{"type":"string"},"userName":{"type":"string"},"phone":{"type":"string"},"address":{"type":"string"},"consignee":{"type":"string"},"cancelReason":{"type":"string"},"rejectionReason":{"type":"string"},"cancelTime":{"type":"string","format":"date-time"},"estimatedDeliveryTime":{"type":"string","format":"date-time"},"deliveryStatus":{"type":"integer","format":"int32"},"deliveryTime":{"type":"string","format":"date-time"},"packAmount":{"type":"integer","format":"int32"},"tablewareNumber":{"type":"integer","format":"int32"},"tablewareStatus":{"type":"integer","format":"int32"},"orderDishes":{"type":"string"},"orderDetailList":{"type":"array","items":{"$ref":"#/components/schemas/OrderDetail"}}}},"ResultOrderVO":{"type":"object","properties":{"code":{"type":"integer","format":"int32"},"msg":{"type":"string"},"data":{"$ref":"#/components/schemas/OrderVO"}}},"PageResultOrderVO":{"type":"object","properties":{"total":{"type":"integer","format":"int64"},"records":{"type":"array","items":{"$ref":"#/components/schemas/OrderVO"}}}},"ResultPageResultOrderVO":{"type":"object","properties":{"code":{"type":"integer","format":"int32"},"msg":{"type":"string"},"data":{"$ref":"#/components/schemas/PageResultOrderVO"}}},"DishVO":{"type":"object","properties":{"id":{"type":"integer","format":"int64"},"name":{"type":"string"},"categoryId":{"type":"integer","format":"int64"},"price":{"type":"number"},"image":{"type":"string"},"description":{"type":"string"},"status":{"type":"integer","format":"int32"},"updateTime":{"type":"string","format":"date-time"},"categoryName":{"type":"string"},"flavors":{"type":"array","items":{"$ref":"#/components/schemas/DishFlavor"}}}},"ResultListDishVO":{"type":"object","properties":{"code":{"type":"integer","format":"int32"},"msg":{"type":"string"},"data":{"type":"array","items":{"$ref":"#/components/schemas/DishVO"}}}},"Category":{"type":"object","properties":{"id":{"type":"integer","format":"int64"},"type":{"type":"integer","format":"int32"},"name":{"type":"string"},"sort":{"type":"integer","format":"int32"},"status":{"type":"integer","format":"int32"},"createTime":{"type":"string","format":"date-time"},"updateTime":{"type":"string","format":"date-time"},"createUser":{"type":"integer","format":"int64"},"updateUser":{"type":"integer","format":"int64"}}},"ResultListCategory":{"type":"object","properties":{"code":{"type":"integer","format":"int32"},"msg":{"type":"string"},"data":{"type":"array","items":{"$ref":"#/components/schemas/Category"}}}},"ResultAddressBook":{"type":"object","properties":{"code":{"type":"integer","format":"int32"},"msg":{"type":"string"},"data":{"$ref":"#/components/schemas/AddressBook"}}},"ResultListAddressBook":{"type":"object","properties":{"code":{"type":"integer","format":"int32"},"msg":{"type":"string"},"data":{"type":"array","items":{"$ref":"#/components/schemas/AddressBook"}}}},"ResultSetmealOverViewVO":{"type":"object","properties":{"code":{"type":"integer","format":"int32"},"msg":{"type":"string"},"data":{"$ref":"#/components/schemas/SetmealOverViewVO"}}},"SetmealOverViewVO":{"type":"object","properties":{"sold":{"type":"integer","format":"int32"},"discontinued":{"type":"integer","format":"int32"}}},"OrderOverViewVO":{"type":"object","properties":{"waitingOrders":{"type":"integer","format":"int32"},"deliveredOrders":{"type":"integer","format":"int32"},"completedOrders":{"type":"integer","format":"int32"},"cancelledOrders":{"type":"integer","format":"int32"},"allOrders":{"type":"integer","format":"int32"}}},"ResultOrderOverViewVO":{"type":"object","properties":{"code":{"type":"integer","format":"int32"},"msg":{"type":"string"},"data":{"$ref":"#/components/schemas/OrderOverViewVO"}}},"DishOverViewVO":{"type":"object","properties":{"sold":{"type":"integer","format":"int32"},"discontinued":{"type":"integer","format":"int32"}}},"ResultDishOverViewVO":{"type":"object","properties":{"code":{"type":"integer","format":"int32"},"msg":{"type":"string"},"data":{"$ref":"#/components/schemas/DishOverViewVO"}}},"BusinessDataVO":{"type":"object","properties":{"turnover":{"type":"number","format":"double"},"validOrderCount":{"type":"integer","format":"int32"},"orderCompletionRate":{"type":"number","format":"double"},"unitPrice":{"type":"number","format":"double"},"newUsers":{"type":"integer","format":"int32"}}},"ResultBusinessDataVO":{"type":"object","properties":{"code":{"type":"integer","format":"int32"},"msg":{"type":"string"},"data":{"$ref":"#/components/schemas/BusinessDataVO"}}},"ResultSetmealVO":{"type":"object","properties":{"code":{"type":"integer","format":"int32"},"msg":{"type":"string"},"data":{"$ref":"#/components/schemas/SetmealVO"}}},"SetmealVO":{"type":"object","properties":{"id":{"type":"integer","format":"int64"},"categoryId":{"type":"integer","format":"int64"},"name":{"type":"string"},"price":{"type":"number"},"status":{"type":"integer","format":"int32"},"description":{"type":"string"},"image":{"type":"string"},"updateTime":{"type":"string","format":"date-time"},"categoryName":{"type":"string"},"setmealDishes":{"type":"array","items":{"$ref":"#/components/schemas/SetmealDish"}}}},"PageResultSetmealVO":{"type":"object","properties":{"total":{"type":"integer","format":"int64"},"records":{"type":"array","items":{"$ref":"#/components/schemas/SetmealVO"}}}},"ResultPageResultSetmealVO":{"type":"object","properties":{"code":{"type":"integer","format":"int32"},"msg":{"type":"string"},"data":{"$ref":"#/components/schemas/PageResultSetmealVO"}}},"ResultUserReportVO":{"type":"object","properties":{"code":{"type":"integer","format":"int32"},"msg":{"type":"string"},"data":{"$ref":"#/components/schemas/UserReportVO"}}},"UserReportVO":{"type":"object","properties":{"dateList":{"type":"string"},"totalUserList":{"type":"string"},"newUserList":{"type":"string"}}},"ResultTurnoverReportVO":{"type":"object","properties":{"code":{"type":"integer","format":"int32"},"msg":{"type":"string"},"data":{"$ref":"#/components/schemas/TurnoverReportVO"}}},"TurnoverReportVO":{"type":"object","properties":{"dateList":{"type":"string"},"turnoverList":{"type":"string"}}},"ResultSalesTop10ReportVO":{"type":"object","properties":{"code":{"type":"integer","format":"int32"},"msg":{"type":"string"},"data":{"$ref":"#/components/schemas/SalesTop10ReportVO"}}},"SalesTop10ReportVO":{"type":"object","properties":{"nameList":{"type":"string"},"numberList":{"type":"string"}}},"OrderReportVO":{"type":"object","properties":{"dateList":{"type":"string"},"orderCountList":{"type":"string"},"validOrderCountList":{"type":"string"},"totalOrderCount":{"type":"integer","format":"int32"},"validOrderCount":{"type":"integer","format":"int32"},"orderCompletionRate":{"type":"number","format":"double"}}},"ResultOrderReportVO":{"type":"object","properties":{"code":{"type":"integer","format":"int32"},"msg":{"type":"string"},"data":{"$ref":"#/components/schemas/OrderReportVO"}}},"OrderStatisticsVO":{"type":"object","properties":{"toBeConfirmed":{"type":"integer","format":"int32"},"confirmed":{"type":"integer","format":"int32"},"deliveryInProgress":{"type":"integer","format":"int32"}}},"ResultOrderStatisticsVO":{"type":"object","properties":{"code":{"type":"integer","format":"int32"},"msg":{"type":"string"},"data":{"$ref":"#/components/schemas/OrderStatisticsVO"}}},"Employee":{"type":"object","properties":{"id":{"type":"integer","format":"int64"},"username":{"type":"string"},"name":{"type":"string"},"password":{"type":"string"},"phone":{"type":"string"},"sex":{"type":"string"},"idNumber":{"type":"string"},"status":{"type":"integer","format":"int32"},"createTime":{"type":"string","format":"date-time"},"updateTime":{"type":"string","format":"date-time"},"createUser":{"type":"integer","format":"int64"},"updateUser":{"type":"integer","format":"int64"}}},"ResultEmployee":{"type":"object","properties":{"code":{"type":"integer","format":"int32"},"msg":{"type":"string"},"data":{"$ref":"#/components/schemas/Employee"}}},"PageResultEmployee":{"type":"object","properties":{"total":{"type":"integer","format":"int64"},"records":{"type":"array","items":{"$ref":"#/components/schemas/Employee"}}}},"ResultPageResultEmployee":{"type":"object","properties":{"code":{"type":"integer","format":"int32"},"msg":{"type":"string"},"data":{"$ref":"#/components/schemas/PageResultEmployee"}}},"ResultDishVO":{"type":"object","properties":{"code":{"type":"integer","format":"int32"},"msg":{"type":"string"},"data":{"$ref":"#/components/schemas/DishVO"}}},"PageResultDishVO":{"type":"object","properties":{"total":{"type":"integer","format":"int64"},"records":{"type":"array","items":{"$ref":"#/components/schemas/DishVO"}}}},"ResultPageResultDishVO":{"type":"object","properties":{"code":{"type":"integer","format":"int32"},"msg":{"type":"string"},"data":{"$ref":"#/components/schemas/PageResultDishVO"}}},"Dish":{"type":"object","properties":{"id":{"type":"integer","format":"int64"},"name":{"type":"string"},"categoryId":{"type":"integer","format":"int64"},"price":{"type":"number"},"image":{"type":"string"},"description":{"type":"string"},"status":{"type":"integer","format":"int32"},"createTime":{"type":"string","format":"date-time"},"updateTime":{"type":"string","format":"date-time"},"createUser":{"type":"integer","format":"int64"},"updateUser":{"type":"integer","format":"int64"}}},"ResultListDish":{"type":"object","properties":{"code":{"type":"integer","format":"int32"},"msg":{"type":"string"},"data":{"type":"array","items":{"$ref":"#/components/schemas/Dish"}}}},"PageResultCategory":{"type":"object","properties":{"total":{"type":"integer","format":"int64"},"records":{"type":"array","items":{"$ref":"#/components/schemas/Category"}}}},"ResultPageResultCategory":{"type":"object","properties":{"code":{"type":"integer","format":"int32"},"msg":{"type":"string"},"data":{"$ref":"#/components/schemas/PageResultCategory"}}}}},"x-openapi":{"x-setting":{"customCode":200,"language":"zh-CN","enableSwaggerModels":true,"swaggerModelName":"Swagger Models","enableReloadCacheParameter":false,"enableAfterScript":true,"enableDocumentManage":true,"enableVersion":false,"enableRequestCache":true,"enableFilterMultipartApis":false,"enableFilterMultipartApiMethodType":"POST","enableHost":false,"enableHostText":"","enableDynamicParameter":false,"enableDebug":true,"enableFooter":true,"enableFooterCustom":false,"enableSearch":true,"enableOpenApi":true,"enableHomeCustom":false,"enableGroup":true,"enableResponseCode":true},"x-markdownFiles":[]}}